av/utils.pxd
av/frame.pxd
av/opaque.cpython-310-darwin.so
av/logging.cpython-310-darwin.so
av/descriptor.pxd
av/stream.cpython-310-darwin.so
av/packet.pyi
av/buffer.pyi
av/error.pyi
av/bytesource.cpython-310-darwin.so
av/logging.pxd
av/format.pxd
av/_core.pyi
av/bitstream.pxd
av/bitstream.pyi
av/dictionary.cpython-310-darwin.so
av/format.pyi
av/__init__.pxd
av/descriptor.cpython-310-darwin.so
av/logging.pyi
av/error.pxd
av/datasets.py
av/buffer.pxd
av/packet.pxd
av/__init__.py
av/plane.cpython-310-darwin.so
av/descriptor.pyi
av/bytesource.pxd
av/about.py
av/frame.pyi
av/opaque.pxd
av/error.cpython-310-darwin.so
av/option.cpython-310-darwin.so
av/plane.pyi
av/dictionary.pyi
av/option.pxd
av/format.cpython-310-darwin.so
av/packet.cpython-310-darwin.so
av/buffer.cpython-310-darwin.so
av/py.typed
av/stream.pxd
av/stream.pyi
av/utils.cpython-310-darwin.so
av/frame.cpython-310-darwin.so
av/dictionary.pxd
av/option.pyi
av/__main__.py
av/bitstream.cpython-310-darwin.so
av/plane.pxd
av/_core.cpython-310-darwin.so
av/video/frame.pxd
av/video/stream.cpython-310-darwin.so
av/video/reformatter.pxd
av/video/format.pxd
av/video/__init__.pyi
av/video/reformatter.pyi
av/video/format.pyi
av/video/__init__.pxd
av/video/codeccontext.cpython-310-darwin.so
av/video/__init__.py
av/video/reformatter.cpython-310-darwin.so
av/video/plane.cpython-310-darwin.so
av/video/frame.pyi
av/video/plane.pyi
av/video/format.cpython-310-darwin.so
av/video/codeccontext.pxd
av/video/stream.pxd
av/video/stream.pyi
av/video/codeccontext.pyi
av/video/frame.cpython-310-darwin.so
av/video/plane.pxd
av/codec/hwaccel.pyi
av/codec/context.pyi
av/codec/__init__.pxd
av/codec/context.pxd
av/codec/codec.cpython-310-darwin.so
av/codec/hwaccel.cpython-310-darwin.so
av/codec/__init__.py
av/codec/hwaccel.pxd
av/codec/codec.pyi
av/codec/codec.pxd
av/codec/context.cpython-310-darwin.so
av/.dylibs/libSvtAv1Enc.2.2.0.dylib
pyav-14.2.1.dist-info/RECORD
pyav-14.2.1.dist-info/WHEEL
pyav-14.2.1.dist-info/entry_points.txt
pyav-14.2.1.dist-info/AUTHORS.rst
pyav-14.2.1.dist-info/AUTHORS.py
pyav-14.2.1.dist-info/top_level.txt
pyav-14.2.1.dist-info/LICENSE.txt
pyav-14.2.1.dist-info/METADATA
