Metadata-Version: 2.2
Name: pyav
Version: 14.2.1
Summary: Pythonic bindings for FFmpeg's libraries.
Author-email: WyattBlue <wyattblue@auto-editor.com>
License: BSD-3-Clause
Project-URL: Bug Tracker, https://github.com/basswood-io/PyAV/discussions/new?category=4-bugs
Project-URL: Source Code, https://github.com/basswood-io/PyAV
Project-URL: homepage, https://pyav.basswood-io.com
Classifier: Development Status :: 5 - Production/Stable
Classifier: Intended Audience :: Developers
Classifier: License :: OSI Approved :: BSD License
Classifier: Natural Language :: English
Classifier: Operating System :: MacOS :: MacOS X
Classifier: Operating System :: POSIX
Classifier: Operating System :: Unix
Classifier: Operating System :: Microsoft :: Windows
Classifier: Programming Language :: Cython
Classifier: Programming Language :: Python :: 3.10
Classifier: Programming Language :: Python :: 3.11
Classifier: Programming Language :: Python :: 3.12
Classifier: Programming Language :: Python :: 3.13
Classifier: Topic :: Software Development :: Libraries :: Python Modules
Classifier: Topic :: Multimedia :: Sound/Audio
Classifier: Topic :: Multimedia :: Sound/Audio :: Conversion
Classifier: Topic :: Multimedia :: Video
Classifier: Topic :: Multimedia :: Video :: Conversion
Requires-Python: >=3.10
License-File: LICENSE.txt
License-File: AUTHORS.py
License-File: AUTHORS.rst
